shogunfolio/__init__.py
shogunfolio/exceptions.py
shogunfolio/typing.py
shogunfolio/cluster/__init__.py
shogunfolio/cluster/_hierarchical.py
shogunfolio/datasets/__init__.py
shogunfolio/datasets/_base.py
shogunfolio/datasets/data/__init__.py
shogunfolio/distance/__init__.py
shogunfolio/distance/_base.py
shogunfolio/distance/_distance.py
shogunfolio/measures/__init__.py
shogunfolio/measures/_enums.py
shogunfolio/measures/_measures.py
shogunfolio/metrics/__init__.py
shogunfolio/metrics/_scorer.py
shogunfolio/model_selection/__init__.py
shogunfolio/model_selection/_combinatorial.py
shogunfolio/model_selection/_validation.py
shogunfolio/model_selection/_walk_forward.py
shogunfolio/moments/__init__.py
shogunfolio/moments/covariance/__init__.py
shogunfolio/moments/covariance/_base.py
shogunfolio/moments/covariance/_covariance.py
shogunfolio/moments/expected_returns/__init__.py
shogunfolio/moments/expected_returns/_base.py
shogunfolio/moments/expected_returns/_expected_returns.py
shogunfolio/optimization/__init__.py
shogunfolio/optimization/_base.py
shogunfolio/optimization/cluster/__init__.py
shogunfolio/optimization/cluster/_nco.py
shogunfolio/optimization/cluster/hierarchical/__init__.py
shogunfolio/optimization/cluster/hierarchical/_base.py
shogunfolio/optimization/cluster/hierarchical/_herc.py
shogunfolio/optimization/cluster/hierarchical/_hrp.py
shogunfolio/optimization/convex/__init__.py
shogunfolio/optimization/convex/_base.py
shogunfolio/optimization/convex/_distributionally_robust.py
shogunfolio/optimization/convex/_maximum_diversification.py
shogunfolio/optimization/convex/_mean_risk.py
shogunfolio/optimization/convex/_risk_budgeting.py
shogunfolio/optimization/ensemble/__init__.py
shogunfolio/optimization/ensemble/_base.py
shogunfolio/optimization/ensemble/_stacking.py
shogunfolio/optimization/naive/__init__.py
shogunfolio/optimization/naive/_naive.py
shogunfolio/population/__init__.py
shogunfolio/population/_population.py
shogunfolio/portfolio/__init__.py
shogunfolio-0.1.0.dist-info/LICENSE
shogunfolio-0.1.0.dist-info/METADATA
shogunfolio-0.1.0.dist-info/WHEEL
shogunfolio-0.1.0.dist-info/top_level.txt
shogunfolio-0.1.0.dist-info/RECORD
