Metadata-Version: 2.1
Name: shogunfolio
Version: 0.1.0
Summary: Portfolio optimization built on top of scikit-learn
Home-page: https://github.com/jialuechen/shogunfolio
Author: Jialue Chen
Author-email: Hugo Delatte <jialuechen@outlook.com>
Maintainer-email: Hugo Delatte <jialuechen@outlook.com>
License: BSD 2-Clause License
Project-URL: API Reference, https://www.shogunfolio.org/api_reference.html
Project-URL: Documentation, https://www.shogunfolio.org
Project-URL: Tutorials, https://www.shogunfolio.org
Project-URL: Repository, https://github.com/shogunfolio/shogunfolio
Keywords: portfolio,optimization,optimisation,finance,asset,allocation,quantitative,quant,investment,strategy,machine-learning,scikit-learn,data-mining,data-science
Classifier: Intended Audience :: Developers
Classifier: Intended Audience :: Science/Research
Classifier: Intended Audience :: Financial and Insurance Industry
Classifier: License :: OSI Approved :: BSD License
Classifier: Operating System :: Unix
Classifier: Operating System :: Microsoft :: Windows
Classifier: Operating System :: MacOS
Classifier: Programming Language :: Python
Classifier: Programming Language :: Python :: 3
Classifier: Programming Language :: Python :: 3.10
Classifier: Programming Language :: Python :: 3.11
Classifier: Programming Language :: Python :: 3.12
Classifier: Topic :: Scientific/Engineering :: Mathematics
Classifier: Topic :: Office/Business :: Financial :: Investment
Classifier: Topic :: Software Development
Requires-Python: >=3.10
License-File: LICENSE
Requires-Dist: numpy >=1.23.4
Requires-Dist: scipy >=1.8.0
Requires-Dist: pandas >=1.4.1
Requires-Dist: cvxpy >=1.4.1
Requires-Dist: scikit-learn >=1.3.2
Requires-Dist: joblib >=1.3.2
Requires-Dist: plotly >=5.15.0
Provides-Extra: docs
Requires-Dist: Sphinx ; extra == 'docs'
Requires-Dist: sphinx-gallery ; extra == 'docs'
Requires-Dist: sphinx-design ; extra == 'docs'
Requires-Dist: pydata-sphinx-theme ==0.13.3 ; extra == 'docs'
Requires-Dist: matplotlib ; extra == 'docs'
Requires-Dist: kaleido ; extra == 'docs'
Requires-Dist: sphinx-copybutton ; extra == 'docs'
Requires-Dist: numpydoc ; extra == 'docs'
Requires-Dist: sphinx-togglebutton ; extra == 'docs'
Requires-Dist: sphinx-favicon ; extra == 'docs'
Requires-Dist: sphinx-prompt ; extra == 'docs'
Requires-Dist: sphinxext.opengraph ; extra == 'docs'
Requires-Dist: sphinx-sitemap ; extra == 'docs'
Provides-Extra: tests
Requires-Dist: pytest ; extra == 'tests'
Requires-Dist: pytest-cov ; extra == 'tests'
Requires-Dist: ruff ; extra == 'tests'
